parambokeh/.version
parambokeh/__init__.py
parambokeh/__main__.py
parambokeh/util.py
parambokeh/view.py
parambokeh/widgets.py
parambokeh/examples/apps/bokeh/simple.py
parambokeh/examples/apps/django2/README.md
parambokeh/examples/apps/django2/manage.py
parambokeh/examples/apps/django2/sliders.png
parambokeh/examples/apps/django2/project/__init__.py
parambokeh/examples/apps/django2/project/settings.py
parambokeh/examples/apps/django2/project/urls.py
parambokeh/examples/apps/django2/project/wsgi.py
parambokeh/examples/apps/django2/sliders/__init__.py
parambokeh/examples/apps/django2/sliders/admin.py
parambokeh/examples/apps/django2/sliders/apps.py
parambokeh/examples/apps/django2/sliders/bk_config.py
parambokeh/examples/apps/django2/sliders/bk_sliders.py
parambokeh/examples/apps/django2/sliders/models.py
parambokeh/examples/apps/django2/sliders/sinewave.py
parambokeh/examples/apps/django2/sliders/tests.py
parambokeh/examples/apps/django2/sliders/urls.py
parambokeh/examples/apps/django2/sliders/views.py
parambokeh/examples/apps/django2/sliders/migrations/__init__.py
parambokeh/examples/apps/django2/sliders/templates/base.html
parambokeh/examples/user_guide/Bokeh_Apps.ipynb
parambokeh/examples/user_guide/Django_Apps.ipynb
parambokeh/examples/user_guide/Introduction.ipynb
parambokeh/examples/user_guide/JSONInit.ipynb
parambokeh/examples/user_guide/View_Parameters.ipynb
parambokeh/examples/user_guide/simple.png
parambokeh/examples/user_guide/sliders.png
parambokeh/tests/__init__.py
parambokeh/tests/test_dummy.py
parambokeh-0.2.3.dist-info/LICENSE.txt
parambokeh-0.2.3.dist-info/METADATA
parambokeh-0.2.3.dist-info/RECORD
parambokeh-0.2.3.dist-info/WHEEL
parambokeh-0.2.3.dist-info/entry_points.txt
parambokeh-0.2.3.dist-info/top_level.txt
