Metadata-Version: 2.1
Name: parambokeh
Version: 0.2.3
Summary: ParamBokeh provides an easy way to generate a UI for param based classes in the notebook or on bokeh server.
Home-page: https://parambokeh.pyviz.org
Author: PyViz
Author-email: holoviews@gmail.com
Maintainer: PyViz
Maintainer-email: holoviews@gmail.com
License: BSD 3-Clause License
Project-URL: Bug Tracker, https://github.com/ioam/parambokeh/issues
Project-URL: Documentation, https://parambokeh.pyviz.org
Project-URL: Source Code, https://github.com/ioam/parambokeh
Platform: UNKNOWN
Classifier: License :: OSI Approved :: BSD License
Classifier: Operating System :: OS Independent
Classifier: Programming Language :: Python
Classifier: Programming Language :: Python :: 2.7
Classifier: Programming Language :: Python :: 3.5
Classifier: Programming Language :: Python :: 3.6
Classifier: Development Status :: 4 - Beta
Requires-Python: >=2.7
Provides-Extra: tests
Provides-Extra: doc
Provides-Extra: examples
